cntop.py
cntop-0.1.3.dist-info/licenses/LICENSE
cntop-0.1.3.dist-info/METADATA
cntop-0.1.3.dist-info/WHEEL
cntop-0.1.3.dist-info/entry_points.txt
cntop-0.1.3.dist-info/top_level.txt
cntop-0.1.3.dist-info/RECORD
