Metadata-Version: 2.4
Name: cntop
Version: 0.1.3
Summary: A top-like tool to show Ceph network information
Requires-Python: >=3.12
License-File: LICENSE
Requires-Dist: pydantic>=2.10.6
Requires-Dist: rich>=13.9.4
Requires-Dist: textual>=2.1.2
Dynamic: license-file
